my_first_trial_model/__init__.py
my_first_trial_model/model.py
my_first_trial_model/utils.py
its_a_trial-1.0.2.dist-info/METADATA
its_a_trial-1.0.2.dist-info/WHEEL
its_a_trial-1.0.2.dist-info/top_level.txt
its_a_trial-1.0.2.dist-info/RECORD
