Metadata-Version: 2.1
Name: its-a-trial
Version: 1.0.2
Summary: A package for your DL model
Home-page: https://github.com/MM21B038/my_first_trial_model
Author: MM21B038
Author-email: mm21b038@smail.iitm.ac.in
Classifier: Programming Language :: Python :: 3
Classifier: License :: OSI Approved :: MIT License
Classifier: Operating System :: OS Independent
Requires-Dist: tensorflow
Requires-Dist: numpy
Requires-Dist: Pillow
